securityriskcard/__init__.py
securityriskcard/__main__.py
tests/__init__.py
tests/regression_data_test.py
tests/regression_score_test.py
securityriskcard-0.0.6.dist-info/LICENSE
securityriskcard-0.0.6.dist-info/METADATA
securityriskcard-0.0.6.dist-info/WHEEL
securityriskcard-0.0.6.dist-info/top_level.txt
securityriskcard-0.0.6.dist-info/RECORD
