Metadata-Version: 2.1
Name: securityriskcard
Version: 0.0.6
Summary: Conversion from scorecard ratings to risk ratings.
Home-page: https://github.com/morphysm/securityriskcard
Author: Cyberfame Team
Author-email: 0x4480@cyberfame.io
License: AGPL-3.0
License-File: LICENSE
